[
  {
    "id": "1dce675d-38bb-46e0-a9f0-2f68e8365895",
    "data": [
      {
        "text": "yes",
        "userDefined": false
      }
    ],
    "isTemplate": false,
    "count": 0,
    "updated": 0
  },
  {
    "id": "7b469adc-fa9c-41b2-af7b-1126470c7720",
    "data": [
      {
        "text": "okay",
        "userDefined": false
      }
    ],
    "isTemplate": false,
    "count": 0,
    "updated": 0
  },
  {
    "id": "2f009ab3-082b-4b69-8803-ae8b8e3a0ead",
    "data": [
      {
        "text": "it\u0027",
        "meta": "@sys.ignore",
        "userDefined": true
      },
      {
        "text": "s ",
        "userDefined": false
      },
      {
        "text": "fine",
        "meta": "@sys.ignore",
        "userDefined": true
      }
    ],
    "isTemplate": false,
    "count": 0,
    "updated": 0
  },
  {
    "id": "da02e062-37d6-4db2-af83-7f3e228a7d73",
    "data": [
      {
        "text": "okie dokie",
        "userDefined": false
      }
    ],
    "isTemplate": false,
    "count": 0,
    "updated": 0
  },
  {
    "id": "4662d0fe-9267-44f8-890b-cc06c8244225",
    "data": [
      {
        "text": "yeah",
        "userDefined": false
      }
    ],
    "isTemplate": false,
    "count": 0,
    "updated": 0
  },
  {
    "id": "b32084c6-502d-4b3e-b40f-1d00fff2e076",
    "data": [
      {
        "text": "exactly",
        "userDefined": false
      }
    ],
    "isTemplate": false,
    "count": 1,
    "updated": 0
  },
  {
    "id": "57e3779f-7e0b-441d-9628-8c72e61af01b",
    "data": [
      {
        "text": "yes ",
        "userDefined": false
      },
      {
        "text": "for sure",
        "meta": "@sys.ignore",
        "userDefined": true
      }
    ],
    "isTemplate": false,
    "count": 0,
    "updated": 0
  },
  {
    "id": "8cde844e-7561-4977-9cb2-a8f4141c8470",
    "data": [
      {
        "text": "yeah ",
        "userDefined": false
      },
      {
        "text": "sure",
        "meta": "@sys.ignore",
        "userDefined": true
      }
    ],
    "isTemplate": false,
    "count": 0,
    "updated": 0
  },
  {
    "id": "b6603e3f-51b4-4e5f-9f05-988568a04b0f",
    "data": [
      {
        "text": "yeah ",
        "userDefined": false
      },
      {
        "text": "of",
        "meta": "@sys.ignore",
        "userDefined": true
      },
      {
        "text": " course",
        "userDefined": false
      }
    ],
    "isTemplate": false,
    "count": 0,
    "updated": 0
  },
  {
    "id": "810b74f0-8357-4766-a165-545542cd4bc6",
    "data": [
      {
        "text": "I guess",
        "userDefined": false
      }
    ],
    "isTemplate": false,
    "count": 0,
    "updated": 0
  },
  {
    "id": "5c2d6547-712e-44d8-b1ac-1635ae9e51ba",
    "data": [
      {
        "text": "ya",
        "userDefined": false
      }
    ],
    "isTemplate": false,
    "count": 0,
    "updated": 0
  },
  {
    "id": "da0e56e1-1ac9-450f-a850-afe5ea6c4e41",
    "data": [
      {
        "text": "yeh",
        "userDefined": false
      }
    ],
    "isTemplate": false,
    "count": 0,
    "updated": 0
  },
  {
    "id": "1954104e-bdaf-4135-b8ce-01f45b327752",
    "data": [
      {
        "text": "ok go ahead",
        "userDefined": false
      }
    ],
    "isTemplate": false,
    "count": 0,
    "updated": 0
  },
  {
    "id": "384388b1-d6f4-4d56-9f68-78ca0ec53b2f",
    "data": [
      {
        "text": "ok",
        "userDefined": false
      }
    ],
    "isTemplate": false,
    "count": 0,
    "updated": 0
  },
  {
    "id": "35d6aed3-c8b2-4213-ab81-290670d72503",
    "data": [
      {
        "text": "why not",
        "userDefined": false
      }
    ],
    "isTemplate": false,
    "count": 0,
    "updated": 0
  },
  {
    "id": "0b17a6a7-31c2-4f0e-bf24-e808335d3a6d",
    "data": [
      {
        "text": "sure",
        "meta": "@sys.ignore",
        "userDefined": true
      },
      {
        "text": " is",
        "userDefined": false
      }
    ],
    "isTemplate": false,
    "count": 0,
    "updated": 0
  },
  {
    "id": "1b394619-49c8-40fe-b51a-01e8c55ad718",
    "data": [
      {
        "text": "yes ",
        "userDefined": false
      },
      {
        "text": "sure",
        "meta": "@sys.ignore",
        "userDefined": true
      }
    ],
    "isTemplate": false,
    "count": 0,
    "updated": 0
  },
  {
    "id": "cee5a0c4-f2e6-4058-8c39-b8b8c76fc4ab",
    "data": [
      {
        "text": "yes ",
        "userDefined": false
      },
      {
        "text": "thank you",
        "meta": "@sys.ignore",
        "userDefined": true
      }
    ],
    "isTemplate": false,
    "count": 0,
    "updated": 0
  },
  {
    "id": "fdf5570f-5174-4c57-9422-25ffb3219b79",
    "data": [
      {
        "text": "ok ",
        "userDefined": false
      },
      {
        "text": "sure",
        "meta": "@sys.ignore",
        "userDefined": true
      }
    ],
    "isTemplate": false,
    "count": 0,
    "updated": 0
  },
  {
    "id": "61283f1d-90d3-4a99-9b42-73c0b664e61f",
    "data": [
      {
        "text": "okay sounds ",
        "userDefined": false
      },
      {
        "text": "good",
        "meta": "@sys.ignore",
        "userDefined": true
      }
    ],
    "isTemplate": false,
    "count": 0,
    "updated": 0
  },
  {
    "id": "2b014d83-b7b6-415d-acbf-bc6cbe3f5fb3",
    "data": [
      {
        "text": "definitely",
        "userDefined": false
      }
    ],
    "isTemplate": false,
    "count": 0,
    "updated": 0
  },
  {
    "id": "e2f1a95e-9e23-43f4-ac54-7d99e7fbf7e7",
    "data": [
      {
        "text": "yes ",
        "userDefined": false
      },
      {
        "text": "it",
        "meta": "@sys.ignore",
        "userDefined": true
      },
      {
        "text": " is correct",
        "userDefined": false
      }
    ],
    "isTemplate": false,
    "count": 0,
    "updated": 0
  },
  {
    "id": "8ac1a7b4-65b7-4d72-af78-6721fe99761f",
    "data": [
      {
        "text": "yes definitely",
        "userDefined": false
      }
    ],
    "isTemplate": false,
    "count": 0,
    "updated": 0
  },
  {
    "id": "7bc1048d-d3a6-4072-9645-5f9b616d86a3",
    "data": [
      {
        "text": "that\u0027s correct",
        "userDefined": false
      }
    ],
    "isTemplate": false,
    "count": 0,
    "updated": 0
  },
  {
    "id": "1ab16651-50cc-491d-88d2-02ba4bfc4efb",
    "data": [
      {
        "text": "of",
        "meta": "@sys.ignore",
        "userDefined": true
      },
      {
        "text": " course why not",
        "userDefined": false
      }
    ],
    "isTemplate": false,
    "count": 0,
    "updated": 0
  },
  {
    "id": "fb5a28b7-3396-4d15-a186-f0184ed7ed8a",
    "data": [
      {
        "text": "certainly",
        "userDefined": false
      }
    ],
    "isTemplate": false,
    "count": 0,
    "updated": 0
  },
  {
    "id": "a21091e5-a851-478a-adc1-f3ee52a2793a",
    "data": [
      {
        "text": "yeah that\u0027s right",
        "userDefined": false
      }
    ],
    "isTemplate": false,
    "count": 0,
    "updated": 0
  },
  {
    "id": "a8f48144-05fa-4553-9d11-243218066db6",
    "data": [
      {
        "text": "do ",
        "userDefined": false
      },
      {
        "text": "it",
        "meta": "@sys.ignore",
        "userDefined": false
      }
    ],
    "isTemplate": false,
    "count": 0,
    "updated": 0
  },
  {
    "id": "bbdc7902-de5d-41d9-a7d1-8323f9b11752",
    "data": [
      {
        "text": "yup",
        "userDefined": false
      }
    ],
    "isTemplate": false,
    "count": 3,
    "updated": 0
  },
  {
    "id": "311af048-df50-4edc-ba3a-236fa4aeb0b2",
    "data": [
      {
        "text": "okay then",
        "userDefined": false
      }
    ],
    "isTemplate": false,
    "count": 0,
    "updated": 0
  },
  {
    "id": "b383a405-2727-4b6f-9d3c-46d3db14f3f4",
    "data": [
      {
        "text": "yes I do",
        "userDefined": false
      }
    ],
    "isTemplate": false,
    "count": 1,
    "updated": 0
  },
  {
    "id": "065f9fe1-d092-40ae-9d73-1fd4f92e0ea5",
    "data": [
      {
        "text": "I do",
        "userDefined": false
      }
    ],
    "isTemplate": false,
    "count": 0,
    "updated": 0
  },
  {
    "id": "2509a23c-86cf-4a88-9d28-b122f4d784f9",
    "data": [
      {
        "text": "affirmative",
        "userDefined": false
      }
    ],
    "isTemplate": false,
    "count": 0,
    "updated": 0
  },
  {
    "id": "a79605f8-1bf3-4124-823e-e4cfcd053914",
    "data": [
      {
        "text": "yes you ",
        "userDefined": false
      },
      {
        "text": "may",
        "meta": "@sys.ignore",
        "userDefined": true
      }
    ],
    "isTemplate": false,
    "count": 0,
    "updated": 0
  },
  {
    "id": "586670a8-c6ae-4d97-999d-5c60be029d0f",
    "data": [
      {
        "text": "yes ",
        "userDefined": false
      },
      {
        "text": "it",
        "meta": "@sys.ignore",
        "userDefined": true
      },
      {
        "text": " is",
        "userDefined": false
      }
    ],
    "isTemplate": false,
    "count": 1,
    "updated": 0
  },
  {
    "id": "4ea495bb-dcdf-4eb4-aef5-9d01a5c95152",
    "data": [
      {
        "text": "go for ",
        "userDefined": false
      },
      {
        "text": "it",
        "meta": "@sys.ignore",
        "userDefined": false
      }
    ],
    "isTemplate": false,
    "count": 0,
    "updated": 0
  },
  {
    "id": "a7b5aa10-938e-49bd-a925-d7fac83200a7",
    "data": [
      {
        "text": "yes this is correct",
        "userDefined": false
      }
    ],
    "isTemplate": false,
    "count": 0,
    "updated": 0
  },
  {
    "id": "da7d9747-6e7a-4ed5-ba36-a068334a4621",
    "data": [
      {
        "text": "go ahead",
        "userDefined": false
      }
    ],
    "isTemplate": false,
    "count": 0,
    "updated": 0
  },
  {
    "id": "9b250163-6b9c-4704-93ab-4789bc40b45b",
    "data": [
      {
        "text": "confirmed",
        "userDefined": false
      }
    ],
    "isTemplate": false,
    "count": 0,
    "updated": 0
  },
  {
    "id": "b96ad62d-ac41-4289-bf20-cfcbdd8f5e84",
    "data": [
      {
        "text": "ok yes",
        "userDefined": false
      }
    ],
    "isTemplate": false,
    "count": 0,
    "updated": 0
  },
  {
    "id": "abed585e-3fdf-485c-b4e7-bcac20619276",
    "data": [
      {
        "text": "yes right",
        "userDefined": false
      }
    ],
    "isTemplate": false,
    "count": 0,
    "updated": 0
  },
  {
    "id": "be3746b9-9f4c-4a1d-9ce0-5884dbbef368",
    "data": [
      {
        "text": "ok you can",
        "userDefined": false
      }
    ],
    "isTemplate": false,
    "count": 0,
    "updated": 0
  },
  {
    "id": "1d86f5c2-7435-478a-885c-029c45a3f0b8",
    "data": [
      {
        "text": "yeah ",
        "userDefined": false
      },
      {
        "text": "I\u0027m",
        "meta": "@sys.ignore",
        "userDefined": true
      },
      {
        "text": " ",
        "userDefined": false
      },
      {
        "text": "sure",
        "meta": "@sys.ignore",
        "userDefined": true
      }
    ],
    "isTemplate": false,
    "count": 0,
    "updated": 0
  },
  {
    "id": "e1f00f8e-2e1a-4b08-b252-7621c9f2c45f",
    "data": [
      {
        "text": "that s okay",
        "userDefined": false
      }
    ],
    "isTemplate": false,
    "count": 0,
    "updated": 0
  },
  {
    "id": "04e72376-f6cd-4897-bbff-53909dc6ef5c",
    "data": [
      {
        "text": "yes that\u0027s ",
        "userDefined": false
      },
      {
        "text": "fine",
        "meta": "@sys.ignore",
        "userDefined": true
      }
    ],
    "isTemplate": false,
    "count": 0,
    "updated": 0
  },
  {
    "id": "1298f07a-4adf-4cb8-9ff2-2fbfb49edae0",
    "data": [
      {
        "text": "okay that\u0027s ",
        "userDefined": false
      },
      {
        "text": "fine",
        "meta": "@sys.ignore",
        "userDefined": true
      }
    ],
    "isTemplate": false,
    "count": 0,
    "updated": 0
  },
  {
    "id": "4446575e-de3b-4dde-a86e-c61d7b1e2320",
    "data": [
      {
        "text": "okey",
        "userDefined": false
      }
    ],
    "isTemplate": false,
    "count": 1,
    "updated": 0
  },
  {
    "id": "f912b828-06f4-454e-80a9-e5d17d7790a7",
    "data": [
      {
        "text": "yeah right",
        "userDefined": false
      }
    ],
    "isTemplate": false,
    "count": 0,
    "updated": 0
  },
  {
    "id": "05b29afb-dac0-4e96-a69f-ce1ac0488166",
    "data": [
      {
        "text": "obviously",
        "userDefined": false
      }
    ],
    "isTemplate": false,
    "count": 0,
    "updated": 0
  },
  {
    "id": "2b21f95c-9a47-4af4-ae99-df63fadc24d9",
    "data": [
      {
        "text": "yes indeed",
        "userDefined": false
      }
    ],
    "isTemplate": false,
    "count": 0,
    "updated": 0
  },
  {
    "id": "d36f2fa4-2892-4583-a7b3-69596a939ac0",
    "data": [
      {
        "text": "alrighty",
        "userDefined": false
      }
    ],
    "isTemplate": false,
    "count": 0,
    "updated": 0
  },
  {
    "id": "5de59cfc-e2e1-4a1a-9c26-de4e67a85cf2",
    "data": [
      {
        "text": "yes ",
        "userDefined": false
      },
      {
        "text": "of",
        "meta": "@sys.ignore",
        "userDefined": true
      },
      {
        "text": " course",
        "userDefined": false
      }
    ],
    "isTemplate": false,
    "count": 0,
    "updated": 0
  },
  {
    "id": "142240a1-64e5-4b06-8f71-dc54d687b472",
    "data": [
      {
        "text": "sounds good",
        "userDefined": false
      }
    ],
    "isTemplate": false,
    "count": 0,
    "updated": 0
  },
  {
    "id": "b3584571-2b43-4c17-aa2a-00fb1f92bd1d",
    "data": [
      {
        "text": "all",
        "meta": "@sys.ignore",
        "userDefined": true
      },
      {
        "text": " ",
        "userDefined": false
      },
      {
        "text": "right",
        "meta": "@sys.ignore",
        "userDefined": true
      }
    ],
    "isTemplate": false,
    "count": 0,
    "updated": 0
  },
  {
    "id": "c105504f-33cb-4a50-aa08-7c3464570173",
    "data": [
      {
        "text": "nevermind",
        "meta": "@sys.ignore",
        "userDefined": true
      },
      {
        "text": " its okay",
        "userDefined": false
      }
    ],
    "isTemplate": false,
    "count": 0,
    "updated": 0
  },
  {
    "id": "96fbbd08-02a3-41c5-a118-d3cca549e75d",
    "data": [
      {
        "text": "this is correct",
        "userDefined": false
      }
    ],
    "isTemplate": false,
    "count": 0,
    "updated": 0
  },
  {
    "id": "f2f0aac1-4406-4fa9-9b43-36a571e3e3a6",
    "data": [
      {
        "text": "yep",
        "userDefined": false
      }
    ],
    "isTemplate": false,
    "count": 0,
    "updated": 0
  },
  {
    "id": "57246620-3f88-434c-aa17-ac6b0959f493",
    "data": [
      {
        "text": "yap",
        "userDefined": false
      }
    ],
    "isTemplate": false,
    "count": 0,
    "updated": 0
  },
  {
    "id": "6e6e7390-f7a2-4df6-a2ed-6a4eecb5d49e",
    "data": [
      {
        "text": "I ",
        "userDefined": false
      },
      {
        "text": "don\u0027",
        "meta": "@sys.ignore",
        "userDefined": true
      },
      {
        "text": "t mind",
        "userDefined": false
      }
    ],
    "isTemplate": false,
    "count": 0,
    "updated": 0
  },
  {
    "id": "52217afb-99c7-47ca-91dc-46c18711e17f",
    "data": [
      {
        "text": "confirm",
        "userDefined": false
      }
    ],
    "isTemplate": false,
    "count": 0,
    "updated": 0
  },
  {
    "id": "c91399dd-b55e-432d-bb5b-b9fefc083bd0",
    "data": [
      {
        "text": "sure",
        "meta": "@sys.ignore",
        "userDefined": true
      },
      {
        "text": " thing",
        "userDefined": false
      }
    ],
    "isTemplate": false,
    "count": 0,
    "updated": 0
  },
  {
    "id": "7188a3ee-aafb-46cc-bf44-c09712739e17",
    "data": [
      {
        "text": "sure",
        "meta": "@sys.ignore",
        "userDefined": true
      },
      {
        "text": " why not",
        "userDefined": false
      }
    ],
    "isTemplate": false,
    "count": 0,
    "updated": 0
  },
  {
    "id": "153ba861-41de-4c99-80d8-cdb01440994b",
    "data": [
      {
        "text": "yes correct",
        "userDefined": false
      }
    ],
    "isTemplate": false,
    "count": 0,
    "updated": 0
  },
  {
    "id": "5e653027-3291-466c-8723-2b1bdc83dd0f",
    "data": [
      {
        "text": "ok ",
        "userDefined": false
      },
      {
        "text": "thank you",
        "meta": "@sys.ignore",
        "userDefined": true
      }
    ],
    "isTemplate": false,
    "count": 0,
    "updated": 0
  },
  {
    "id": "d99dba36-15e6-414b-a9f2-8f90cf833673",
    "data": [
      {
        "text": "sure",
        "meta": "@sys.ignore",
        "userDefined": false
      }
    ],
    "isTemplate": false,
    "count": 0,
    "updated": 0
  },
  {
    "id": "48df03bb-bcd8-4fdc-bd85-b5288729a761",
    "data": [
      {
        "text": "looks ",
        "userDefined": false
      },
      {
        "text": "good",
        "meta": "@sys.ignore",
        "userDefined": true
      }
    ],
    "isTemplate": false,
    "count": 0,
    "updated": 0
  },
  {
    "id": "58cfdbed-6363-47ea-a886-3f8b4fd6aeee",
    "data": [
      {
        "text": "yes I agree",
        "userDefined": false
      }
    ],
    "isTemplate": false,
    "count": 0,
    "updated": 0
  },
  {
    "id": "6743a27f-f920-4b67-a62a-e669bdbd79f8",
    "data": [
      {
        "text": "k",
        "userDefined": false
      }
    ],
    "isTemplate": false,
    "count": 1,
    "updated": 0
  },
  {
    "id": "63cd2301-de8d-4127-a14a-beea163c9973",
    "data": [
      {
        "text": "yeah exactly",
        "userDefined": false
      }
    ],
    "isTemplate": false,
    "count": 0,
    "updated": 0
  },
  {
    "id": "db2958b9-8108-4783-9fe7-226743220b1c",
    "data": [
      {
        "text": "I agree",
        "userDefined": false
      }
    ],
    "isTemplate": false,
    "count": 0,
    "updated": 0
  },
  {
    "id": "049ef576-5c5e-4573-aa9c-db029f8ada3e",
    "data": [
      {
        "text": "yeah go ahead",
        "userDefined": false
      }
    ],
    "isTemplate": false,
    "count": 0,
    "updated": 0
  },
  {
    "id": "0747a6a5-7a43-462a-a6de-a596167cfc0f",
    "data": [
      {
        "text": "right",
        "userDefined": false
      }
    ],
    "isTemplate": false,
    "count": 0,
    "updated": 0
  },
  {
    "id": "e8af34d6-2421-4b4d-a4b4-d65f660cf250",
    "data": [
      {
        "text": "absolutely",
        "userDefined": false
      }
    ],
    "isTemplate": false,
    "count": 0,
    "updated": 0
  },
  {
    "id": "67af8856-9a5b-4959-a4c4-b23c18aaeb5e",
    "data": [
      {
        "text": "yes I would like to",
        "userDefined": false
      }
    ],
    "isTemplate": false,
    "count": 0,
    "updated": 0
  },
  {
    "id": "b5555046-d60b-4a73-a8a6-604b1971c19e",
    "data": [
      {
        "text": "please do",
        "userDefined": false
      }
    ],
    "isTemplate": false,
    "count": 0,
    "updated": 0
  },
  {
    "id": "e6b1458e-4904-4dcb-bcb4-03948e94c151",
    "data": [
      {
        "text": "correct",
        "userDefined": false
      }
    ],
    "isTemplate": false,
    "count": 1,
    "updated": 0
  },
  {
    "id": "190b8e80-2c9f-412e-a5fa-9359aa14a355",
    "data": [
      {
        "text": "that is ok",
        "userDefined": false
      }
    ],
    "isTemplate": false,
    "count": 0,
    "updated": 0
  },
  {
    "id": "547531e0-2c79-432c-8248-baf28d7a0fb9",
    "data": [
      {
        "text": "ye",
        "userDefined": false
      }
    ],
    "isTemplate": false,
    "count": 0,
    "updated": 0
  },
  {
    "id": "7b3f6567-d049-4201-ac78-0abc0ce97363",
    "data": [
      {
        "text": "yea",
        "userDefined": false
      }
    ],
    "isTemplate": false,
    "count": 1,
    "updated": 0
  },
  {
    "id": "0c78044f-a2a8-4f57-bbf0-be3968adc17b",
    "data": [
      {
        "text": "of",
        "meta": "@sys.ignore",
        "userDefined": false
      },
      {
        "text": " course",
        "userDefined": false
      }
    ],
    "isTemplate": false,
    "count": 0,
    "updated": 0
  },
  {
    "id": "2bb32f6f-e204-45aa-9d97-e32ad9158b1f",
    "data": [
      {
        "text": "oh yes",
        "userDefined": false
      }
    ],
    "isTemplate": false,
    "count": 1,
    "updated": 0
  },
  {
    "id": "67537854-86d8-4439-8a24-f96979cc4905",
    "data": [
      {
        "text": "I think so",
        "userDefined": false
      }
    ],
    "isTemplate": false,
    "count": 0,
    "updated": 0
  }
]