[
  {
    "id": "c55aeaab-bfef-4333-9925-dd580aede9f7",
    "data": [
      {
        "text": "I shouldn\u0027t care about this",
        "userDefined": false
      }
    ],
    "isTemplate": false,
    "count": 0,
    "updated": 0
  },
  {
    "id": "a2ef8c89-a9dd-4b87-9112-f33a00b2abf3",
    "data": [
      {
        "text": "I ",
        "userDefined": false
      },
      {
        "text": "don\u0027t",
        "meta": "@sys.ignore",
        "userDefined": false
      },
      {
        "text": " care",
        "userDefined": false
      }
    ],
    "isTemplate": false,
    "count": 0,
    "updated": 0
  },
  {
    "id": "af42261f-52b1-4e0e-baf8-e3e4315ef0d0",
    "data": [
      {
        "text": "I do not care",
        "userDefined": false
      }
    ],
    "isTemplate": false,
    "count": 0,
    "updated": 0
  },
  {
    "id": "5047a2c0-28f5-4b29-ae3f-f9d95e6aceb8",
    "data": [
      {
        "text": "whatever",
        "userDefined": false
      }
    ],
    "isTemplate": false,
    "count": 0,
    "updated": 0
  },
  {
    "id": "37684ef2-2c39-4e4c-aaea-b7371c6922db",
    "data": [
      {
        "text": "not caring",
        "userDefined": false
      }
    ],
    "isTemplate": false,
    "count": 0,
    "updated": 0
  },
  {
    "id": "5b59d0c9-f85e-4e6b-b882-fdef7a8fb300",
    "data": [
      {
        "text": "don",
        "meta": "@sys.ignore",
        "userDefined": false
      },
      {
        "text": "\u0027t care at ",
        "userDefined": false
      },
      {
        "text": "all",
        "meta": "@sys.ignore",
        "userDefined": false
      }
    ],
    "isTemplate": false,
    "count": 0,
    "updated": 0
  },
  {
    "id": "317f9295-b637-4ca1-ba1b-f1a1a47fb860",
    "data": [
      {
        "text": "I ",
        "userDefined": false
      },
      {
        "text": "don",
        "meta": "@sys.ignore",
        "userDefined": false
      },
      {
        "text": "\u0027t care at ",
        "userDefined": false
      },
      {
        "text": "all",
        "meta": "@sys.ignore",
        "userDefined": false
      }
    ],
    "isTemplate": false,
    "count": 0,
    "updated": 0
  },
  {
    "id": "52b060b4-cb18-4eb6-b1fe-55a59088f82e",
    "data": [
      {
        "text": "not care at ",
        "userDefined": false
      },
      {
        "text": "all",
        "meta": "@sys.ignore",
        "userDefined": false
      }
    ],
    "isTemplate": false,
    "count": 0,
    "updated": 0
  },
  {
    "id": "385fe8b3-be07-48e1-a665-d16d3cbaccc0",
    "data": [
      {
        "text": "not caring at ",
        "userDefined": false
      },
      {
        "text": "all",
        "meta": "@sys.ignore",
        "userDefined": false
      }
    ],
    "isTemplate": false,
    "count": 0,
    "updated": 0
  }
]