[
  {
    "id": "a3964773-542d-4e1b-84cb-83dd28cb9d92",
    "data": [
      {
        "text": "happy",
        "meta": "@sys.ignore",
        "userDefined": false
      }
    ],
    "isTemplate": false,
    "count": 0,
    "updated": 0
  },
  {
    "id": "14753931-0de5-462c-806f-78e012e416e4",
    "data": [
      {
        "text": "if you\u0027re ",
        "userDefined": false
      },
      {
        "text": "happy",
        "meta": "@sys.ignore",
        "userDefined": false
      },
      {
        "text": " then I\u0027m ",
        "userDefined": false
      },
      {
        "text": "happy",
        "meta": "@sys.ignore",
        "userDefined": false
      }
    ],
    "isTemplate": false,
    "count": 0,
    "updated": 0
  },
  {
    "id": "57f99eed-597d-420d-94eb-da96d25b3acb",
    "data": [
      {
        "text": "I\u0027m happy to see you",
        "userDefined": false
      }
    ],
    "isTemplate": false,
    "count": 0,
    "updated": 0
  },
  {
    "id": "eade848a-70d6-44eb-bf8c-f037a498f9d5",
    "data": [
      {
        "text": "I\u0027m happy to help",
        "userDefined": false
      }
    ],
    "isTemplate": false,
    "count": 0,
    "updated": 0
  },
  {
    "id": "08468cf3-e4fb-4742-a397-ea92e60557ef",
    "data": [
      {
        "text": "I am ",
        "userDefined": false
      },
      {
        "text": "happy",
        "meta": "@sys.ignore",
        "userDefined": false
      }
    ],
    "isTemplate": false,
    "count": 0,
    "updated": 0
  },
  {
    "id": "78527d29-9ffa-44b5-aef7-b49edc5d517f",
    "data": [
      {
        "text": "I\u0027m ",
        "userDefined": false
      },
      {
        "text": "happy",
        "meta": "@sys.ignore",
        "userDefined": false
      },
      {
        "text": " to see you",
        "userDefined": false
      }
    ],
    "isTemplate": false,
    "count": 0,
    "updated": 0
  },
  {
    "id": "b159f8c4-fdcb-4389-94ac-9951bf5b7bf2",
    "data": [
      {
        "text": "I\u0027m ",
        "userDefined": false
      },
      {
        "text": "happy",
        "meta": "@sys.ignore",
        "userDefined": false
      },
      {
        "text": " for you",
        "userDefined": false
      }
    ],
    "isTemplate": false,
    "count": 0,
    "updated": 0
  }
]